puzzle15ai/__init__.py
puzzle15ai/main_window.py
puzzle15ai/node.py
puzzle15ai/tree.py
puzzle15ai/ui_mainwindow.py
puzzle15ai-0.1.14.dist-info/LICENSE.md
puzzle15ai-0.1.14.dist-info/METADATA
puzzle15ai-0.1.14.dist-info/WHEEL
puzzle15ai-0.1.14.dist-info/entry_points.txt
puzzle15ai-0.1.14.dist-info/top_level.txt
puzzle15ai-0.1.14.dist-info/RECORD
