Metadata-Version: 2.1
Name: puzzle15ai
Version: 0.1.14
Summary: Puzzle15 AI solver with A* search algorithm
Home-page: https://github.com/SajjadAemmi/Puzzle15AI
Author: Sajjad Aemmi
Author-email: sajjadaemmi@gmail.com
License-File: LICENSE.md
Requires-Dist: pyside6
Requires-Dist: numpy
